{"web":{"client_id":"296468202865-5agi0vopshqv3o9pecbnocuo50ll6cvs.apps.googleusercontent.com","project_id":"fsnd-catagoryapp","auth_uri":"https://accounts.google.com/o/oauth2/auth","token_uri":"https://accounts.google.com/o/oauth2/token","auth_provider_x509_cert_url":"https://www.googleapis.com/oauth2/v1/certs","client_secret":"IPUtpqw3YRAbf4f1DpGOkQ_-","redirect_uris":["http://www.example.com/oauth2callback","http://localhost:5000/login","http://localhost:5000/gconnect"],"javascript_origins":["http://localhost:5000","http://127.0.0.1:5000","http://www.example.com"]}}